{"title":"Wicker Park","uid":3929313,"size":2018316804,"categoryP":"video","categoryS":"movies","magnet":"?xt=urn:btih:0b12fa18d25334f200b4f9025744e543fb7c7607&amp;dn=Wicker+Park&amp;tr=udp%3A%2F%2Ftracker.openbittorrent.com%3A80&amp;tr=udp%3A%2F%2Fopen.demonii.com%3A1337&amp;tr=udp%3A%2F%2Ftracker.coppersurfer.tk%3A6969&amp;tr=udp%3A%2F%2Fexodus.desync.com%3A6969","seeders":0,"leechers":1,"uploader":"bdfortin","files":18,"time":1197348767,"description":"Wicker Park is a 2004 romantic psychological thriller directed by Paul McGuigan. It&amp;#039;s a remake of the 1996 French movie L&amp;#039;Appartement.\n\n\nThis file includes the movie and the soundtrack.\n\n\nMovie ripped with HandBrake on the iPod setting (640x272, 1500 kbps, iTunes chapter markers) with the commentary as the secondary audio (use QuickTime or VLC to access it).\n\nMusic encoded with FLAC 8 using Toast.\n\n\n\nEnjoy.","torrent":{"xt":"urn:btih:0b12fa18d25334f200b4f9025744e543fb7c7607","amp;dn":"Wicker+Park","amp;tr":["udp%3A%2F%2Ftracker.openbittorrent.com%3A80","udp%3A%2F%2Fopen.demonii.com%3A1337","udp%3A%2F%2Ftracker.coppersurfer.tk%3A6969","udp%3A%2F%2Fexodus.desync.com%3A6969"],"infoHash":"0b12fa18d25334f200b4f9025744e543fb7c7607","infoHashBuffer":{"type":"Buffer","data":[11,18,250,24,210,83,52,242,0,180,249,2,87,68,229,67,251,124,118,7]},"announce":[],"urlList":[]}}