{"title":"I Am Legend H.264","uid":3967901,"size":1124525644,"categoryP":"video","categoryS":"movies","magnet":"?xt=urn:btih:2e98e1d549bf68007bb3136609f02a77a2645aba&amp;dn=I+Am+Legend+H.264&amp;tr=udp%3A%2F%2Ftracker.openbittorrent.com%3A80&amp;tr=udp%3A%2F%2Fopen.demonii.com%3A1337&amp;tr=udp%3A%2F%2Ftracker.coppersurfer.tk%3A6969&amp;tr=udp%3A%2F%2Fexodus.desync.com%3A6969","seeders":0,"leechers":0,"uploader":"Dr.Sne","files":1,"time":1199835954,"description":"Name:\t\tI Am Legend (2007)\nVideo Codec:\tH.264\nVideo Bitrate:\t1100 kbps\nAudio Codec:\tAAC-LC\nAudio Bitrate:\t400kbps (5.1 Channel)\nResolution:\t854x362 Anamorphic PAR\nLanguage:\t         English\nContainer:\tMOV\nIMDB: &lt;a href=&quot;\thttp://imdb.com/title/tt0480249/&quot; rel=&quot;nofollow&quot; target=&quot;_NEW&quot;&gt;\thttp://imdb.com/title/tt0480249/&lt;/a&gt;","torrent":{"xt":"urn:btih:2e98e1d549bf68007bb3136609f02a77a2645aba","amp;dn":"I+Am+Legend+H.264","amp;tr":["udp%3A%2F%2Ftracker.openbittorrent.com%3A80","udp%3A%2F%2Fopen.demonii.com%3A1337","udp%3A%2F%2Ftracker.coppersurfer.tk%3A6969","udp%3A%2F%2Fexodus.desync.com%3A6969"],"infoHash":"2e98e1d549bf68007bb3136609f02a77a2645aba","infoHashBuffer":{"type":"Buffer","data":[46,152,225,213,73,191,104,0,123,179,19,102,9,240,42,119,162,100,90,186]},"announce":[],"urlList":[]}}