{"title":"Hong Kong Phooey [nostalgiatracker]","uid":3351519,"size":684448485,"categoryP":"video","categoryS":"tv_shows","magnet":"?xt=urn:btih:46dddd92a62f472b7597313e182514162799d1f1&amp;dn=Hong+Kong+Phooey+%5Bnostalgiatracker%5D&amp;tr=udp%3A%2F%2Ftracker.openbittorrent.com%3A80&amp;tr=udp%3A%2F%2Fopen.demonii.com%3A1337&amp;tr=udp%3A%2F%2Ftracker.coppersurfer.tk%3A6969&amp;tr=udp%3A%2F%2Fexodus.desync.com%3A6969","seeders":0,"leechers":1,"uploader":"Urabewe","files":8,"time":1120357655,"description":"Hong Kong Phooey, if you haven't seen it check the IMDB link above.\n\nA description here is not really needed, it's Hong Kong Phooey, 'nuff said. There are 8 episodes, 2 are in the same file and the quality is pretty good considering these are pretty old.\n\nIf you haven't already, check out Nostalgia Tracker, has some stuff you haven't seen in a long time.\n\nhttp://s11.invisionfree.com/nostalgiatracker","torrent":{"xt":"urn:btih:46dddd92a62f472b7597313e182514162799d1f1","amp;dn":"Hong+Kong+Phooey+%5Bnostalgiatracker%5D","amp;tr":["udp%3A%2F%2Ftracker.openbittorrent.com%3A80","udp%3A%2F%2Fopen.demonii.com%3A1337","udp%3A%2F%2Ftracker.coppersurfer.tk%3A6969","udp%3A%2F%2Fexodus.desync.com%3A6969"],"infoHash":"46dddd92a62f472b7597313e182514162799d1f1","infoHashBuffer":{"type":"Buffer","data":[70,221,221,146,166,47,71,43,117,151,49,62,24,37,20,22,39,153,209,241]},"announce":[],"urlList":[]}}