{"title":"Eilert_Pilarm_Slang_Dig_I_Vaggen","uid":3366657,"size":14588444,"categoryP":"audio","categoryS":"music","magnet":"?xt=urn:btih:4f1aa6dcdf1a2199a9b822269d0d9c51ee2930f1&amp;dn=Eilert_Pilarm_Slang_Dig_I_Vaggen&amp;tr=udp%3A%2F%2Ftracker.openbittorrent.com%3A80&amp;tr=udp%3A%2F%2Fopen.demonii.com%3A1337&amp;tr=udp%3A%2F%2Ftracker.coppersurfer.tk%3A6969&amp;tr=udp%3A%2F%2Fexodus.desync.com%3A6969","seeders":0,"leechers":1,"uploader":"DooMarN","files":3,"time":1123427424,"description":"Henrik Ahlen fr&amp;aring;n &amp;Ouml;rebro spelade in denna k&amp;auml;rleksf&amp;ouml;rklaring\ntill sin blivande fru p&amp;aring; svensexan","torrent":{"xt":"urn:btih:4f1aa6dcdf1a2199a9b822269d0d9c51ee2930f1","amp;dn":"Eilert_Pilarm_Slang_Dig_I_Vaggen","amp;tr":["udp%3A%2F%2Ftracker.openbittorrent.com%3A80","udp%3A%2F%2Fopen.demonii.com%3A1337","udp%3A%2F%2Ftracker.coppersurfer.tk%3A6969","udp%3A%2F%2Fexodus.desync.com%3A6969"],"infoHash":"4f1aa6dcdf1a2199a9b822269d0d9c51ee2930f1","infoHashBuffer":{"type":"Buffer","data":[79,26,166,220,223,26,33,153,169,184,34,38,157,13,156,81,238,41,48,241]},"announce":[],"urlList":[]}}