{"title":"Above and Beyond - Trance Around The World 200 (01-25-08)","uid":3995745,"size":115208098,"categoryP":"audio","categoryS":"music","magnet":"?xt=urn:btih:54b1473a891312c990d6615a515ecd0aed1e5d57&amp;dn=Above+and+Beyond+-+Trance+Around+The+World+200+%2801-25-08%29&amp;tr=udp%3A%2F%2Ftracker.openbittorrent.com%3A80&amp;tr=udp%3A%2F%2Fopen.demonii.com%3A1337&amp;tr=udp%3A%2F%2Ftracker.coppersurfer.tk%3A6969&amp;tr=udp%3A%2F%2Fexodus.desync.com%3A6969","seeders":0,"leechers":0,"uploader":"jscottyh","files":2,"time":1201301068,"description":"Trance Around The World with Above &amp; Beyond #200\n25th January 2008\n\n1. Yimaz Altanhan &quot;80&amp;#039;s&quot; [Ozcar Can Mix] (Anjunabeats)\n2. Ridgewalkers feat El &quot;Find&quot; [Andy Moor Mix] (Armada)\n3. Endre &quot;I Kill For You&quot; [Probspot Remix] (Anjunabeats)\n4. Lange &quot;Songless&quot; [Boy Hagemann Remix] (Lange Recordings)\n5. Tilt &quot;The World Doesn?t Know&quot; (Lost Language)\n6. Andy Moor &quot;Halcyon&quot; (Anjunabeats)\n7. Sarah McLachlan &quot;World On Fire&quot; [Junkie XL Mix] (Nettwerk)\n8. Super8 + DJ Tab &quot;Helsinki Scorching&quot; (Anjunabeats)\n9. Sufjan Stevens vs. Signalrunners &quot;Chicago&quot; (CDR)\n10. Above &amp; Beyond with Andy Moor &quot;Air For Life&quot; [original mix] (Anjunabeats)\n11. Cosmic Gate &quot;Body Of Conflict&quot; [Cosmic Gate Club Mix] (Black Hole)\n12. Gabriel &amp; Dresden &quot;Tracking Treasure Down&quot; (Organised Nature)\n13. Armin van Buuren &quot;Control Freak&quot; [Sander van Doorn Remix] (Armind)\n14. Rob Mooney &quot;Feelin Electro&quot; [Valentino Kanzyani Remix] (Punch Funk)\n15. Aalto &quot;5&quot; (Anjunabeats)\n16. Signalrunners &quot;Aria Epica&quot; [Bart Claesson Remix] (Anjunabeats)\n17. Above &amp; Beyond &quot;Can&amp;#039;t Sleep&quot; (Anjunabeats)\n18. Maor Levi &quot;Shining&quot; (CDR)\n19. Tranquility Base &quot;Razorfish&quot; (Anjunabeats)\n20. 2 Divine &quot;Black Is The Colour&quot; [Coco &amp; Green Mix] (Anjunabeats)\n21. Whiteroom &quot;The White Room&quot; (Liquid Asset)\n22. Bolier &amp; Coenraad &quot;Mohawk&quot; (Intuition Recordings)\n23. DT8 &quot;Destination&quot; [Above &amp; Beyond Remix] (Mondo)\n24. Aalto &quot;Rush&quot; [Super8 vs Orkidea Remix] (Anjunabeats)\n25. Cassandra Fox &quot;Touch Me&quot; [Mike Koglin &amp; Jono Grant Remix] (Sony)\n26. Alt + F4 &quot;Alt + F4&quot; (Anjunabeats)\n27. Sunny Lax &quot;PUMA&quot; (Anjunabeats)\n28. Mike Shiver &quot;Morning Drive&quot; (Anjunabeats)\n29. Kaste &quot;Desert Eagle&quot; [Smith &amp; Pledger Remix] (Anjunabeats)\n30. Smith &amp; Pledger &quot;Northern Lights&quot; (Anjunabeats)\n31. Nitromethane &quot;Religion&quot; (CDR)\n32. Above &amp; Beyond pres. Unkle Petter &quot;So Many Faces&quot; (CDR)\n33. Summer Sessions Feat. Michele Smith &quot;Blossom&quot; (E-TCR)\n34. Art of Trance &quot;Mongoose&quot; (Tek^tonik Remix) (Platipus)\n35. Oliver Smith &quot;Nimbus&quot; (Anjunabeats)\n36. Armin vs Mike &quot;Intruder&quot; (ASOT)\n37. Tiesto feat Jes &quot;Everything&quot; (Black Hole)\n38. Boom Jinx &quot;Remember September&quot; [Duderstadt Mix] (Anjunadeep)\n39. The Thrillseekers Feat Aruna &amp;#039;Waiting Here For You&amp;#039; (Adjusted Music)\n40. First State &quot;Falling&quot; (Black Hole)\n41. Oceanlab &quot;Sirens Of The Sea&quot; [Above &amp; Beyond&amp;#039;s Original Mix] (Anjunabeats)\n42. Above &amp; Beyond &quot;Stealing Time&quot; [A&amp;B Deep Club Mix] (Anjunabeats)\n43. Above &amp; Beyond &quot;No One On Earth&quot; [Gabriel &amp; Dresden Remix] (Anjunabeats)\n44. Madonna &quot;What It Feels Like For A Girl&quot; [Above &amp; Beyond Remix] (Warner Brothers)\n45. Stephen J Kroos &quot;Phantazmz&quot; (Anjunabeats)\n46. Young Parisians Feat. Ben Lost &quot;Jump The Next Train&quot; [Kyau vs Albert Remix]\n47. Super8 &quot;Alba&quot; (Anjunabeats)\n48. Super8 &amp; Tab &quot;Suru&quot; (Anjunabeats)\n49. Super8 &quot;Get Off&quot; (Anjunabeats)\n50. Matt Hardwick vs Smith &amp; Pledger ?Connected? (Anjunabeats)\n51. Breakfast &quot;The Sunlight&quot; (Flashover)\n52. Above &amp; Beyond pres. Tranquility Base &quot;Surrender&quot; (Anjunabeats)\n53. Oceanlab &quot;Satellite&quot; (Sony BMG)\n54. Nitrous Oxide &quot;North Pole&quot; (Anjunabeats)\n55. Daniel Kandi &quot;Child&quot; (Anjunabeats)\n56. Above &amp; Beyond &quot;Good For Me&quot; [A&amp;B Club mix] (Anjunabeats)\n57. Luminary &quot;Amsterdam&quot; [Smith &amp; Pledger Remix] (Anjunabeats)\n58. Daniel Kandi &quot;Breathe&quot; (Anjunabeats)\n59. Sander van Doorn &quot;S.O.S.&quot; (Spinnin&amp;#039;)\n60. Gabriel &amp; Dresden &quot;Dangerous Power&quot; (Organized Nature)\n61. Above &amp; Beyond &quot;Oceanic&quot; [Super8 &amp; Tab Remix] (Anjunabeats)\n62. Signum &quot;The Timelord&quot; (ASOT)\n63. Britney Spears &quot;Everytime&quot; [Above &amp; Beyond Club Mix] (Sony)\n64. Shah &amp; Cosmo Pres. Purple Mood &quot;One Night In Tokyo&quot; (Anjunabeats)\n65. Mark Pledger vs. Matt Hardwick Feat Melinda Gareh &quot;Fallen Tides&quot; (Anjunabeats)\n66. Remy &amp; Roland Klinkenberg &quot;Monday Groove&quot; (Armada)\n67. Mike Koglin vs. Jono Grant &quot;Sequential&quot; (Anjunabeats)\n68. Adam Nickey &quot;Never Gone&quot; (Anjunabeats)\n69. P.O.S &quot;Gravity&quot; (Anjunabeats)\n70. Nitromethane &quot;Time To Die&quot; [Seraque Remix] (Anjunabeats)\n71. Above &amp; Beyond &quot;Alone Tonight&quot; (Anjunabeats)","torrent":{"xt":"urn:btih:54b1473a891312c990d6615a515ecd0aed1e5d57","amp;dn":"Above+and+Beyond+-+Trance+Around+The+World+200+%2801-25-08%29","amp;tr":["udp%3A%2F%2Ftracker.openbittorrent.com%3A80","udp%3A%2F%2Fopen.demonii.com%3A1337","udp%3A%2F%2Ftracker.coppersurfer.tk%3A6969","udp%3A%2F%2Fexodus.desync.com%3A6969"],"infoHash":"54b1473a891312c990d6615a515ecd0aed1e5d57","infoHashBuffer":{"type":"Buffer","data":[84,177,71,58,137,19,18,201,144,214,97,90,81,94,205,10,237,30,93,87]},"announce":[],"urlList":[]}}