{"title":"Road.to.Avonlea.S01E04.DVDRip.XviD-aAF","uid":3360609,"size":366794566,"categoryP":"video","categoryS":"tv_shows","magnet":"?xt=urn:btih:5e37fa186370a5b1df42af3bf6bb3b0cf1546976&amp;dn=Road.to.Avonlea.S01E04.DVDRip.XviD-aAF&amp;tr=udp%3A%2F%2Ftracker.openbittorrent.com%3A80&amp;tr=udp%3A%2F%2Fopen.demonii.com%3A1337&amp;tr=udp%3A%2F%2Ftracker.coppersurfer.tk%3A6969&amp;tr=udp%3A%2F%2Fexodus.desync.com%3A6969","seeders":0,"leechers":0,"uploader":"QazzaQY2K","files":2,"time":1122243547,"description":"You may distribute this torrent to every site/torrent engine u know of \n        that still don't got it and please come on idle in our new Avonlea fan IRC \n        Channel.. let's enjoy this together the more the merryer it is.\n\n\n        IRC     - mIRC, any othere IRC client\n        Sever   - EFnet\n        Channel - #Avonlea\n\n        Release Information     \n     \n        Release Date....: 2005.05.01\n        Air Date........: 1990.01.07\n        \n        Source..........: DVD\n        Network.........: CBC\n        Video...........: XviD\n        Video Bitrate...: 1514 kbit/s\n        Audio...........: MP3 (VBR)\n        Audio Bitrate...: 32-320 kbps\n        Duration........: 44 minutes\n        Resolution......: 512x384\n        Aspect Ratio....: 4:3\n        Frame Rate......: 23.976\n        \n        Size............: CD&amp;frac12;: 25x15mb\n        Genre...........: Drama/Adventure/Family/Mstery/Romance\n        iMDB Rating.....: -.-\n        URL.............: http://imdb.com/title/tt0098900/\n\n\n\n        Plot Summary\n\n        .4 The Materializing of Duncan McTavish\n        Everyone in Avonlea knows everything about everyone. Exasperated, Marilla \n        Cuthbert, &quot;creates&quot; a beau for the ladies of the sewing circle. To \n        Marilla's distress, a traveling salesman with the same name she 'made up' \n        shows up in town. Marilla faces Duncan McTavish and tells him the truth. \n        Realizing the predicament she is in, Duncan helps her Marilla stop all of \n        the wagging tongues in Avonlea.\n","torrent":{"xt":"urn:btih:5e37fa186370a5b1df42af3bf6bb3b0cf1546976","amp;dn":"Road.to.Avonlea.S01E04.DVDRip.XviD-aAF","amp;tr":["udp%3A%2F%2Ftracker.openbittorrent.com%3A80","udp%3A%2F%2Fopen.demonii.com%3A1337","udp%3A%2F%2Ftracker.coppersurfer.tk%3A6969","udp%3A%2F%2Fexodus.desync.com%3A6969"],"infoHash":"5e37fa186370a5b1df42af3bf6bb3b0cf1546976","infoHashBuffer":{"type":"Buffer","data":[94,55,250,24,99,112,165,177,223,66,175,59,246,187,59,12,241,84,105,118]},"announce":[],"urlList":[]}}