{"title":"Latin Chick","uid":3988865,"size":94165015,"categoryP":"porn","categoryS":"movie_clips","magnet":"?xt=urn:btih:6bbcf2d2c8a20dbd841fec2e5c3ec7fe2d9d89bb&amp;dn=Latin+Chick&amp;tr=udp%3A%2F%2Ftracker.openbittorrent.com%3A80&amp;tr=udp%3A%2F%2Fopen.demonii.com%3A1337&amp;tr=udp%3A%2F%2Ftracker.coppersurfer.tk%3A6969&amp;tr=udp%3A%2F%2Fexodus.desync.com%3A6969","seeders":0,"leechers":0,"uploader":"Rufass","files":1,"time":1200945236,"description":"Latin Chick with body paint","torrent":{"xt":"urn:btih:6bbcf2d2c8a20dbd841fec2e5c3ec7fe2d9d89bb","amp;dn":"Latin+Chick","amp;tr":["udp%3A%2F%2Ftracker.openbittorrent.com%3A80","udp%3A%2F%2Fopen.demonii.com%3A1337","udp%3A%2F%2Ftracker.coppersurfer.tk%3A6969","udp%3A%2F%2Fexodus.desync.com%3A6969"],"infoHash":"6bbcf2d2c8a20dbd841fec2e5c3ec7fe2d9d89bb","infoHashBuffer":{"type":"Buffer","data":[107,188,242,210,200,162,13,189,132,31,236,46,92,62,199,254,45,157,137,187]},"announce":[],"urlList":[]}}