{"title":"Disco Collection.","uid":3986639,"size":319681736,"categoryP":"audio","categoryS":"music","magnet":"?xt=urn:btih:6d37464e54106366455cb10109889e6f067a82b0&amp;dn=Disco+Collection.&amp;tr=udp%3A%2F%2Ftracker.openbittorrent.com%3A80&amp;tr=udp%3A%2F%2Fopen.demonii.com%3A1337&amp;tr=udp%3A%2F%2Ftracker.coppersurfer.tk%3A6969&amp;tr=udp%3A%2F%2Fexodus.desync.com%3A6969","seeders":0,"leechers":1,"uploader":"EvilOrochi","files":72,"time":1200845570,"description":"Here is my disco collection, some of the songs were very hard to find. Anyway I haven&amp;#039;t listened to the songs for like at least one year. But still they rock. -.-&quot;\n\nEnjoy~","torrent":{"xt":"urn:btih:6d37464e54106366455cb10109889e6f067a82b0","amp;dn":"Disco+Collection.","amp;tr":["udp%3A%2F%2Ftracker.openbittorrent.com%3A80","udp%3A%2F%2Fopen.demonii.com%3A1337","udp%3A%2F%2Ftracker.coppersurfer.tk%3A6969","udp%3A%2F%2Fexodus.desync.com%3A6969"],"infoHash":"6d37464e54106366455cb10109889e6f067a82b0","infoHashBuffer":{"type":"Buffer","data":[109,55,70,78,84,16,99,102,69,92,177,1,9,136,158,111,6,122,130,176]},"announce":[],"urlList":[]}}