{"title":"Coupling season 4 DVD (nordic subs)","uid":3994019,"size":4509134848,"categoryP":"video","categoryS":"tv_shows","magnet":"?xt=urn:btih:836d0ee38ec477e0c46ca5cfc958627551f7fc60&amp;dn=Coupling+season+4+DVD+%28nordic+subs%29&amp;tr=udp%3A%2F%2Ftracker.openbittorrent.com%3A80&amp;tr=udp%3A%2F%2Fopen.demonii.com%3A1337&amp;tr=udp%3A%2F%2Ftracker.coppersurfer.tk%3A6969&amp;tr=udp%3A%2F%2Fexodus.desync.com%3A6969","seeders":0,"leechers":1,"uploader":"umpalumpa83","files":11,"time":1201209653,"description":"Coupling UK season 4 DVD\n\nSERIES 4:\n\n1. 9 1/2 minutes\n2. Nightlines\n3. Bed time\n4. Circus of epidurals\n5. The naked living room\n6. 9 1/2 months\n\nLanguege: english\nSubtitles: finnish, swedish, norwegian, danish\n\nIMDB:\n    &lt;a href=&quot;\nhttp://imdb.com/title/tt0237123/&quot; rel=&quot;nofollow&quot; target=&quot;_NEW&quot;&gt;\nhttp://imdb.com/title/tt0237123/&lt;/a&gt;\n\nUser Rating: 9.2/10 (3,513 votes) \n\nThe DVD has been decrypted by Dvdfab decrypter (DVD9 ---&gt; DVD5)\nRegional free\n\nJust burn the files to dvd and enjoy! :D\n\n\nP.S. Be nice and seed.","torrent":{"xt":"urn:btih:836d0ee38ec477e0c46ca5cfc958627551f7fc60","amp;dn":"Coupling+season+4+DVD+%28nordic+subs%29","amp;tr":["udp%3A%2F%2Ftracker.openbittorrent.com%3A80","udp%3A%2F%2Fopen.demonii.com%3A1337","udp%3A%2F%2Ftracker.coppersurfer.tk%3A6969","udp%3A%2F%2Fexodus.desync.com%3A6969"],"infoHash":"836d0ee38ec477e0c46ca5cfc958627551f7fc60","infoHashBuffer":{"type":"Buffer","data":[131,109,14,227,142,196,119,224,196,108,165,207,201,88,98,117,81,247,252,96]},"announce":[],"urlList":[]}}