{"title":"Silent Alarm","uid":3902133,"size":52450112,"categoryP":"audio","categoryS":"music","magnet":"?xt=urn:btih:89a080346871216621baeb952da921e6ccdd2fe8&amp;dn=Silent+Alarm&amp;tr=udp%3A%2F%2Ftracker.openbittorrent.com%3A80&amp;tr=udp%3A%2F%2Fopen.demonii.com%3A1337&amp;tr=udp%3A%2F%2Ftracker.coppersurfer.tk%3A6969&amp;tr=udp%3A%2F%2Fexodus.desync.com%3A6969","seeders":0,"leechers":1,"uploader":"mini1337","files":14,"time":1195622885,"description":"Bloc Party Album Silent Alarm:\n\nTracklist:\n\n   1. &quot;Like Eating Glass&quot; ? 4:20\n   2. &quot;Helicopter&quot; ? 3:40\n   3. &quot;Positive Tension&quot; ? 3:54\n   4. &quot;Banquet&quot; ? 3:22\n   5. &quot;Blue Light&quot; ? 2:47\n   6. &quot;She&amp;#039;s Hearing Voices&quot; ? 3:29\n   7. &quot;This Modern Love&quot; ? 4:25\n   8. &quot;The Pioneers&quot; ? 3:35\n   9. &quot;Price of Gasoline&quot; ? 4:19\n  10. &quot;So Here We Are&quot; ? 3:53\n  11. &quot;Luno&quot; ? 3:57\n  12. &quot;Plans&quot; ? 4:10\n  13. &quot;Compliments&quot; ? 4:43\n\nVirus free. Share and enjoy!","torrent":{"xt":"urn:btih:89a080346871216621baeb952da921e6ccdd2fe8","amp;dn":"Silent+Alarm","amp;tr":["udp%3A%2F%2Ftracker.openbittorrent.com%3A80","udp%3A%2F%2Fopen.demonii.com%3A1337","udp%3A%2F%2Ftracker.coppersurfer.tk%3A6969","udp%3A%2F%2Fexodus.desync.com%3A6969"],"infoHash":"89a080346871216621baeb952da921e6ccdd2fe8","infoHashBuffer":{"type":"Buffer","data":[137,160,128,52,104,113,33,102,33,186,235,149,45,169,33,230,204,221,47,232]},"announce":[],"urlList":[]}}