{"title":"Wigga 4","uid":4007758,"size":69576959,"categoryP":"other","categoryS":"other","magnet":"?xt=urn:btih:9e90d1fc96458231540f239b54cc72846901ee0a&amp;dn=Wigga+4&amp;tr=udp%3A%2F%2Ftracker.openbittorrent.com%3A80&amp;tr=udp%3A%2F%2Fopen.demonii.com%3A1337&amp;tr=udp%3A%2F%2Ftracker.coppersurfer.tk%3A6969&amp;tr=udp%3A%2F%2Fexodus.desync.com%3A6969","seeders":0,"leechers":0,"uploader":"maoh44","files":19,"time":1201920434,"description":"bit of funny shit","torrent":{"xt":"urn:btih:9e90d1fc96458231540f239b54cc72846901ee0a","amp;dn":"Wigga+4","amp;tr":["udp%3A%2F%2Ftracker.openbittorrent.com%3A80","udp%3A%2F%2Fopen.demonii.com%3A1337","udp%3A%2F%2Ftracker.coppersurfer.tk%3A6969","udp%3A%2F%2Fexodus.desync.com%3A6969"],"infoHash":"9e90d1fc96458231540f239b54cc72846901ee0a","infoHashBuffer":{"type":"Buffer","data":[158,144,209,252,150,69,130,49,84,15,35,155,84,204,114,132,105,1,238,10]},"announce":[],"urlList":[]}}