{"title":"Alcohol 120% 1.9.5.3105","uid":3355815,"size":4564978,"categoryP":"applications","categoryS":"windows","magnet":"?xt=urn:btih:ab65e8125bd8bc5f1b1872e65c85e7990d3fcbdd&amp;dn=Alcohol+120%25+1.9.5.3105&amp;tr=udp%3A%2F%2Ftracker.openbittorrent.com%3A80&amp;tr=udp%3A%2F%2Fopen.demonii.com%3A1337&amp;tr=udp%3A%2F%2Ftracker.coppersurfer.tk%3A6969&amp;tr=udp%3A%2F%2Fexodus.desync.com%3A6969","seeders":0,"leechers":0,"uploader":"LuCjUs","files":1,"time":1121273844,"description":"Nowa wersja &amp;#347;wietnego narz&amp;#281;dzia przeznaczonego do tworzenia obraz&amp;oacute;w, emulowania i nagrywania p&amp;#322;yt CD i DVD. Aplikacja umo&amp;#380;liwia zapis p&amp;#322;yt na CD-R/CD-RW/DVD-R/DVD-RW/DVD-RAM/DVD+RW. Alcohol 120% potrafi utworzy&amp;#263; nawet 31 wirtualnych nap&amp;#281;d&amp;oacute;w CD/DVD. Posiada bardzo prosty interfejs (w ca&amp;#322;o&amp;#347;ci w j&amp;#281;zyku polskim). Z jego pomoc&amp;#261; mo&amp;#380;liwe jest r&amp;oacute;wnie&amp;#380; kopiowanie zebezpieczonych p&amp;#322;yt (gry, programy, filmy DVD). Umieszczane w wirtualnym nap&amp;#281;dzie kompakty mog&amp;#261; by&amp;#263; odczytywane z pr&amp;#281;dko&amp;#347;ci&amp;#261; nawet do 200x.","torrent":{"xt":"urn:btih:ab65e8125bd8bc5f1b1872e65c85e7990d3fcbdd","amp;dn":"Alcohol+120%25+1.9.5.3105","amp;tr":["udp%3A%2F%2Ftracker.openbittorrent.com%3A80","udp%3A%2F%2Fopen.demonii.com%3A1337","udp%3A%2F%2Ftracker.coppersurfer.tk%3A6969","udp%3A%2F%2Fexodus.desync.com%3A6969"],"infoHash":"ab65e8125bd8bc5f1b1872e65c85e7990d3fcbdd","infoHashBuffer":{"type":"Buffer","data":[171,101,232,18,91,216,188,95,27,24,114,230,92,133,231,153,13,63,203,221]},"announce":[],"urlList":[]}}