{"title":"Track de Reggae","uid":4014810,"size":170025178,"categoryP":"audio","categoryS":"music","magnet":"?xt=urn:btih:ae24f68f8491874cd5a88808812e98cbeae7ee23&amp;dn=Track+de+Reggae&amp;tr=udp%3A%2F%2Ftracker.openbittorrent.com%3A80&amp;tr=udp%3A%2F%2Fopen.demonii.com%3A1337&amp;tr=udp%3A%2F%2Ftracker.coppersurfer.tk%3A6969&amp;tr=udp%3A%2F%2Fexodus.desync.com%3A6969","seeders":0,"leechers":0,"uploader":"liponidas","files":22,"time":1202303384,"description":"Muscos desconocidos y no tanto muestra el panorama reggae","torrent":{"xt":"urn:btih:ae24f68f8491874cd5a88808812e98cbeae7ee23","amp;dn":"Track+de+Reggae","amp;tr":["udp%3A%2F%2Ftracker.openbittorrent.com%3A80","udp%3A%2F%2Fopen.demonii.com%3A1337","udp%3A%2F%2Ftracker.coppersurfer.tk%3A6969","udp%3A%2F%2Fexodus.desync.com%3A6969"],"infoHash":"ae24f68f8491874cd5a88808812e98cbeae7ee23","infoHashBuffer":{"type":"Buffer","data":[174,36,246,143,132,145,135,76,213,168,136,8,129,46,152,203,234,231,238,35]},"announce":[],"urlList":[]}}