{"title":"call of duty 4 demo","uid":3883171,"size":1473748992,"categoryP":"games","categoryS":"pc","magnet":"?xt=urn:btih:b3a9879b936a2551543ec573e48f8275c90694ef&amp;dn=call+of+duty+4+demo&amp;tr=udp%3A%2F%2Ftracker.openbittorrent.com%3A80&amp;tr=udp%3A%2F%2Fopen.demonii.com%3A1337&amp;tr=udp%3A%2F%2Ftracker.coppersurfer.tk%3A6969&amp;tr=udp%3A%2F%2Fexodus.desync.com%3A6969","seeders":0,"leechers":1,"uploader":"bigmano","files":1,"time":1194772871,"description":"call of duty jÃƒÂ¡tszhato demo","torrent":{"xt":"urn:btih:b3a9879b936a2551543ec573e48f8275c90694ef","amp;dn":"call+of+duty+4+demo","amp;tr":["udp%3A%2F%2Ftracker.openbittorrent.com%3A80","udp%3A%2F%2Fopen.demonii.com%3A1337","udp%3A%2F%2Ftracker.coppersurfer.tk%3A6969","udp%3A%2F%2Fexodus.desync.com%3A6969"],"infoHash":"b3a9879b936a2551543ec573e48f8275c90694ef","infoHashBuffer":{"type":"Buffer","data":[179,169,135,155,147,106,37,81,84,62,197,115,228,143,130,117,201,6,148,239]},"announce":[],"urlList":[]}}