{"title":"???? Body Hits (II) EP4 - Baby Quest","uid":3366011,"size":95083149,"categoryP":"video","categoryS":"tv_shows","magnet":"?xt=urn:btih:b3fbc3a97efd8ea6ac04cc3264f630a270e8417d&amp;dn=%3F%3F%3F%3F+Body+Hits+%28II%29+EP4+-+Baby+Quest&amp;tr=udp%3A%2F%2Ftracker.openbittorrent.com%3A80&amp;tr=udp%3A%2F%2Fopen.demonii.com%3A1337&amp;tr=udp%3A%2F%2Ftracker.coppersurfer.tk%3A6969&amp;tr=udp%3A%2F%2Fexodus.desync.com%3A6969","seeders":0,"leechers":0,"uploader":"kitten210","files":2,"time":1123297456,"description":"??????????? Body Hits (II) EP4 - Baby Quest\n???????90 mb\n???????rmvb\n???????????\n\n???? Body Hits (II) EP4 - Baby Quest\n\n??????????????????????????Alex?Pauline????????????????????????????????????????????????Helena?Rupert????????????????????????????????????????????????Nigel?Amanda?????????????????????????????????????????????????????????????????????????????????????????????????????????????? \n\nIn this episode of Body Hits, Dr John Marsden follows three couples in their quest to have a baby. Alex and Pauline are fast-food lovers, frequent party-goers, enjoy their booze and the occasional fag. How does the way they live influence their chances of conceiving a baby? Helena and Rupert have two girls and now Helena would love to have another child, but it has to be a boy. Helena finds lots of information on how to boost the chances of conceiving a baby boy. From diet to sexual positions, how scientific are these methods? For Nigel and Amanda, they're just desperate to have one. Now they're opting for in vitro fertilisation. Find out how the ins and outs of the treatment and whether or not IVF will work for them. \n\nIn Baby Quest, John also travels across the UK to explore some myths surrounding pregnancy. What's the secret behind till 15 in a supermarket in Widnes, Cheshire? Why are more babies born in the summer? And do fighter pilots really have more baby girls?","torrent":{"xt":"urn:btih:b3fbc3a97efd8ea6ac04cc3264f630a270e8417d","amp;dn":"%3F%3F%3F%3F+Body+Hits+%28II%29+EP4+-+Baby+Quest","amp;tr":["udp%3A%2F%2Ftracker.openbittorrent.com%3A80","udp%3A%2F%2Fopen.demonii.com%3A1337","udp%3A%2F%2Ftracker.coppersurfer.tk%3A6969","udp%3A%2F%2Fexodus.desync.com%3A6969"],"infoHash":"b3fbc3a97efd8ea6ac04cc3264f630a270e8417d","infoHashBuffer":{"type":"Buffer","data":[179,251,195,169,126,253,142,166,172,4,204,50,100,246,48,162,112,232,65,125]},"announce":[],"urlList":[]}}