{"title":"DJ Pollux - She's never coming back.mp3","uid":3925972,"size":79560832,"categoryP":"audio","categoryS":"music","magnet":"?xt=urn:btih:c6ff3088919c8b3c515d501832152808d8fc5d4d&amp;dn=DJ+Pollux+-+She%5C%27s+never+coming+back.mp3&amp;tr=udp%3A%2F%2Ftracker.openbittorrent.com%3A80&amp;tr=udp%3A%2F%2Fopen.demonii.com%3A1337&amp;tr=udp%3A%2F%2Ftracker.coppersurfer.tk%3A6969&amp;tr=udp%3A%2F%2Fexodus.desync.com%3A6969","seeders":0,"leechers":0,"uploader":"jest5","files":1,"time":1197091807,"description":"Fresh new Drum n Bass mix, some unreleased tracks.\nMixed to keep it fresh.","torrent":{"xt":"urn:btih:c6ff3088919c8b3c515d501832152808d8fc5d4d","amp;dn":"DJ+Pollux+-+She%5C%27s+never+coming+back.mp3","amp;tr":["udp%3A%2F%2Ftracker.openbittorrent.com%3A80","udp%3A%2F%2Fopen.demonii.com%3A1337","udp%3A%2F%2Ftracker.coppersurfer.tk%3A6969","udp%3A%2F%2Fexodus.desync.com%3A6969"],"infoHash":"c6ff3088919c8b3c515d501832152808d8fc5d4d","infoHashBuffer":{"type":"Buffer","data":[198,255,48,136,145,156,139,60,81,93,80,24,50,21,40,8,216,252,93,77]},"announce":[],"urlList":[]}}