{"title":"CSI Las Vegas [8x09-10] (XviD asd) EnglishV+NapisyPL - www.tvsho","uid":3939614,"size":250602257,"categoryP":"video","categoryS":"tv_shows","magnet":"?xt=urn:btih:c7ddc03f38b81260db8d1bf0bc80f21246026a8f&amp;dn=CSI+Las+Vegas+%5B8x09-10%5D+%28XviD+asd%29+EnglishV%2BNapisyPL+-+www.tvsho&amp;tr=udp%3A%2F%2Ftracker.openbittorrent.com%3A80&amp;tr=udp%3A%2F%2Fopen.demonii.com%3A1337&amp;tr=udp%3A%2F%2Ftracker.coppersurfer.tk%3A6969&amp;tr=udp%3A%2F%2Fexodus.desync.com%3A6969","seeders":0,"leechers":0,"uploader":"fluidfluid","files":-1,"time":1198055345,"description":"want more?? - visitu us at www.tvshows.yoyo.pl","torrent":{"xt":"urn:btih:c7ddc03f38b81260db8d1bf0bc80f21246026a8f","amp;dn":"CSI+Las+Vegas+%5B8x09-10%5D+%28XviD+asd%29+EnglishV%2BNapisyPL+-+www.tvsho","amp;tr":["udp%3A%2F%2Ftracker.openbittorrent.com%3A80","udp%3A%2F%2Fopen.demonii.com%3A1337","udp%3A%2F%2Ftracker.coppersurfer.tk%3A6969","udp%3A%2F%2Fexodus.desync.com%3A6969"],"infoHash":"c7ddc03f38b81260db8d1bf0bc80f21246026a8f","infoHashBuffer":{"type":"Buffer","data":[199,221,192,63,56,184,18,96,219,141,27,240,188,128,242,18,70,2,106,143]},"announce":[],"urlList":[]}}