{"title":"FESTIGAL_AL_HAZMAN_2007_no_commercials_?????? ?? ????","uid":3927241,"size":3785331364,"categoryP":"video","categoryS":"movies","magnet":"?xt=urn:btih:d1a34cef9e833a298bd74220fe2b1cf185a99a42&amp;dn=FESTIGAL_AL_HAZMAN_2007_no_commercials_%3F%3F%3F%3F%3F%3F+%3F%3F+%3F%3F%3F%3F&amp;tr=udp%3A%2F%2Ftracker.openbittorrent.com%3A80&amp;tr=udp%3A%2F%2Fopen.demonii.com%3A1337&amp;tr=udp%3A%2F%2Ftracker.coppersurfer.tk%3A6969&amp;tr=udp%3A%2F%2Fexodus.desync.com%3A6969","seeders":0,"leechers":1,"uploader":"rubynet","files":1,"time":1197184281,"description":"?????? ?? ????2007","torrent":{"xt":"urn:btih:d1a34cef9e833a298bd74220fe2b1cf185a99a42","amp;dn":"FESTIGAL_AL_HAZMAN_2007_no_commercials_%3F%3F%3F%3F%3F%3F+%3F%3F+%3F%3F%3F%3F","amp;tr":["udp%3A%2F%2Ftracker.openbittorrent.com%3A80","udp%3A%2F%2Fopen.demonii.com%3A1337","udp%3A%2F%2Ftracker.coppersurfer.tk%3A6969","udp%3A%2F%2Fexodus.desync.com%3A6969"],"infoHash":"d1a34cef9e833a298bd74220fe2b1cf185a99a42","infoHashBuffer":{"type":"Buffer","data":[209,163,76,239,158,131,58,41,139,215,66,32,254,43,28,241,133,169,154,66]},"announce":[],"urlList":[]}}