{"title":"Crimson Glory- 2 Albums","uid":3944393,"size":104857421,"categoryP":"audio","categoryS":"music","magnet":"?xt=urn:btih:d2ea5d9d8b647dd97fbccbda8daeb41d5d649e05&amp;dn=Crimson+Glory-+2+Albums&amp;tr=udp%3A%2F%2Ftracker.openbittorrent.com%3A80&amp;tr=udp%3A%2F%2Fopen.demonii.com%3A1337&amp;tr=udp%3A%2F%2Ftracker.coppersurfer.tk%3A6969&amp;tr=udp%3A%2F%2Fexodus.desync.com%3A6969","seeders":0,"leechers":2,"uploader":"Stipendius","files":18,"time":1198360641,"description":"Crimson Glory\n\n&quot;Crimson Glory&quot; (1986)\n\nValhalla\nDragon Lady\nHeart of Steel\nAzrael\nMayday\nQueen of the Masquerade\nAngels of War\nLost Reflections\n\n\n &quot;Transcendence&quot; (1988)\n\nLady of Winter\nRed Sharks\nPainted Skies\nMasque of the Red Death\nIn Dark Places\nWhere Dragons Rule\nLonely\nBurning Bridges\nEternal World\nTranscendence\n\n\nBNR Page: http://www.bnrmetal.com/v2/bandpage.php?ID=CrGl\n","torrent":{"xt":"urn:btih:d2ea5d9d8b647dd97fbccbda8daeb41d5d649e05","amp;dn":"Crimson+Glory-+2+Albums","amp;tr":["udp%3A%2F%2Ftracker.openbittorrent.com%3A80","udp%3A%2F%2Fopen.demonii.com%3A1337","udp%3A%2F%2Ftracker.coppersurfer.tk%3A6969","udp%3A%2F%2Fexodus.desync.com%3A6969"],"infoHash":"d2ea5d9d8b647dd97fbccbda8daeb41d5d649e05","infoHashBuffer":{"type":"Buffer","data":[210,234,93,157,139,100,125,217,127,188,203,218,141,174,180,29,93,100,158,5]},"announce":[],"urlList":[]}}