{"title":"windows","uid":3980914,"size":10764156,"categoryP":"applications","categoryS":"windows","magnet":"?xt=urn:btih:d9cf8ce696f164ae3b592931de67ad5451a71b17&amp;dn=windows&amp;tr=udp%3A%2F%2Ftracker.openbittorrent.com%3A80&amp;tr=udp%3A%2F%2Fopen.demonii.com%3A1337&amp;tr=udp%3A%2F%2Ftracker.coppersurfer.tk%3A6969&amp;tr=udp%3A%2F%2Fexodus.desync.com%3A6969","seeders":0,"leechers":1,"uploader":"flabbott1","files":12,"time":1200542570,"description":"xp and vista keygens and cracks \n\nviva la nation","torrent":{"xt":"urn:btih:d9cf8ce696f164ae3b592931de67ad5451a71b17","amp;dn":"windows","amp;tr":["udp%3A%2F%2Ftracker.openbittorrent.com%3A80","udp%3A%2F%2Fopen.demonii.com%3A1337","udp%3A%2F%2Ftracker.coppersurfer.tk%3A6969","udp%3A%2F%2Fexodus.desync.com%3A6969"],"infoHash":"d9cf8ce696f164ae3b592931de67ad5451a71b17","infoHashBuffer":{"type":"Buffer","data":[217,207,140,230,150,241,100,174,59,89,41,49,222,103,173,84,81,167,27,23]},"announce":[],"urlList":[]}}