{"title":"Discovery Channel MegaWorld Netherlands HDTV XviD FQM","uid":3985123,"size":365260026,"categoryP":"video","categoryS":"tv_shows","magnet":"?xt=urn:btih:f4d4742b8c4a00e88977988fd8221539b32f67eb&amp;dn=Discovery+Channel+MegaWorld+Netherlands+HDTV+XviD+FQM&amp;tr=udp%3A%2F%2Ftracker.openbittorrent.com%3A80&amp;tr=udp%3A%2F%2Fopen.demonii.com%3A1337&amp;tr=udp%3A%2F%2Ftracker.coppersurfer.tk%3A6969&amp;tr=udp%3A%2F%2Fexodus.desync.com%3A6969","seeders":0,"leechers":1,"uploader":"dyslexik","files":1,"time":1200770745,"description":" Â¯Â¦Â¯ Â¦Â¦        Release Type.....: HDTV                                   Â¦Â¦ Â¯Â¦Â¯\n  Â¦  Â¦Â¦ _      Series...........: Discovery Channel MegaWorld          _ Â¦Â¦  Â¦\n  Â¦  Â¦Â¦ _      Genre............: Documentary                          _ Â¦Â¦  Â¦\n     Â¦  Â¦      Episode..........: Unknown                              Â¦  Â¦\n    Â¦Â¦  Â¯      Title............: Netherlands                          Â¯  Â¦Â¦\n    Â¦Â¦         Production Code..: Unknown                                 Â¦Â¦\n    Â¦Â¦         Orig. Air Date...: Unknown                                 Â¦Â¦\n    Â¦Â¦         Release Date.....: 13-Jan-2008                             Â¦Â¦\n    Â¦Â¦         Source...........: 1080i HDTV                              Â¦Â¦\n    Â¦Â¦         Video Format.....: XviD                                    Â¦Â¦\n    Â¦Â¦         Video Resolution.: 624x352                                 Â¦Â¦\n    Â¦Â¦         Video Bitrate....: 920 kbit/s average                      Â¦Â¦\n    Â¦Â¦         Video Framerate..: 29.970 fps                              Â¦Â¦\n  Â¦ Â¦Â¦  Â¦      Audio Format.....: VBR MP3 (Stereo)                     Â¦  Â¦Â¦ Â¦\n  Â¦ Â¦Â¦  Â¯      Audio Bitrate....: 152 kbit/s                           Â¯  Â¦Â¦ Â¦\n  Â¦  Â¦Â¦ Â¦      Audio Sample Rate: 48 KHz                               Â¦ Â¦Â¦  Â¦\n  Â¦  Â¦Â¦ Â¯      Length...........: 44:06.477                            Â¯ Â¦Â¦  Â¦\n _Â¦_ Â¦Â¦ _      Size.............: 365,260,026                          _ Â¦Â¦ _Â¦_\n  Â¯   Â¦ Â¯      Packs............: 25*15MB = 348MB                      Â¯ Â¦   Â¯\n  Â¯  Â¦Â¦        Link.............:                                        Â¦Â¦  Â¯\n     Â¦Â¦Â¦                   Unknown                                      Â¦Â¦Â¦\n    _Â¦Â¦Â¦_                                                              _Â¦Â¦Â¦_\n    Â¦Â¦ Â¯Â¦Â¦____________________________________________________________Â¦Â¦Â¯ Â¦Â¦\n     Â¦Â¦_ Â¦Â¯Â¯Â¯Â¯Â¯Â¯Â¯Â¯Â¯Â¯Â¯Â¯Â¯Â¦Â¦Â¦Â¯Â¯Â¯Â¯Â¯Â¯Â¯Â¯Â¯Â¯Â¯Â¯Â¯Â¯Â¯Â¯Â¯Â¯Â¯Â¯Â¯Â¯Â¯Â¯Â¯Â¯Â¯Â¯Â¦Â¦Â¦Â¯Â¯Â¯Â¯Â¯Â¯Â¯Â¯Â¯Â¯Â¯Â¯Â¯Â¦ _Â¦Â¦\n     Â¦Â¦Â¦Â¦Â¦Â¦Â¦Â¦Â¦Â¦Â¦Â¦Â¦Â¦Â¦Â¦ Â¦ Â¯Â¦Â¦Â¦Â¦Â¦ Â¦    Summary     Â¦ Â¦Â¦Â¦Â¦Â¦Â¯ Â¦ Â¦Â¦Â¦Â¦Â¦Â¦Â¦Â¦Â¦Â¦Â¦Â¦Â¦Â¦Â¦Â¦\n     Â¦Â¦Â¯  ______________  Â¯Â¯                        Â¯Â¯  ______________  Â¯Â¦Â¦\n    Â¦Â¦ _Â¦Â¦Â¯Â¯Â¯Â¯Â¯Â¯Â¯Â¯Â¯Â¯Â¯Â¯Â¯                                  Â¯Â¯Â¯Â¯Â¯Â¯Â¯Â¯Â¯Â¯Â¯Â¯Â¯Â¦Â¦_ Â¦Â¦\n    Â¯Â¦Â¦Â¦Â¯                                                              Â¯Â¦Â¦Â¦Â¯\n     Â¦Â¦Â¦                                                                Â¦Â¦Â¦\n     Â¦Â¦    World&amp;#039;s most powerful tugboats; floating homes; world&amp;#039;s       Â¦Â¦\n     _Â¦    largest flower auction.                                       Â¦_\n     Â¦Â¦                                                                  Â¦Â¦\n     Â¦Â¦Â¦                                                                Â¦Â¦Â¦","torrent":{"xt":"urn:btih:f4d4742b8c4a00e88977988fd8221539b32f67eb","amp;dn":"Discovery+Channel+MegaWorld+Netherlands+HDTV+XviD+FQM","amp;tr":["udp%3A%2F%2Ftracker.openbittorrent.com%3A80","udp%3A%2F%2Fopen.demonii.com%3A1337","udp%3A%2F%2Ftracker.coppersurfer.tk%3A6969","udp%3A%2F%2Fexodus.desync.com%3A6969"],"infoHash":"f4d4742b8c4a00e88977988fd8221539b32f67eb","infoHashBuffer":{"type":"Buffer","data":[244,212,116,43,140,74,0,232,137,119,152,143,216,34,21,57,179,47,103,235]},"announce":[],"urlList":[]}}